type_yaml/_
type_yaml/__init__.py
type_yaml/errors.py
type_yaml/yaml_interpreter.py
type_yaml/yaml_parse.py
type_yaml-0.3.0.dist-info/WHEEL
type_yaml-0.3.0.dist-info/METADATA
type_yaml-0.3.0.dist-info/LICENSE
type_yaml-0.3.0.dist-info/RECORD
