Metadata-Version: 2.1
Name: type-yaml
Version: 0.3.0
Summary: 
Author: nahco314
Author-email: nahco3_ta@yahoo.co.jp
Requires-Python: >=3.8.1,<4.0.0
Classifier: Programming Language :: Python :: 3
Classifier: Programming Language :: Python :: 3.9
Classifier: Programming Language :: Python :: 3.10
Classifier: Programming Language :: Python :: 3.11
Requires-Dist: pyyaml (>=6.0,<7.0)
Requires-Dist: type-parse (>=0.1.0,<0.2.0)
